colorfield/__init__.py
colorfield/fields.py
colorfield/metadata.py
colorfield/serializers.py
colorfield/utils.py
colorfield/validators.py
colorfield/widgets.py
colorfield/locale/en/LC_MESSAGES/django.mo
colorfield/locale/en/LC_MESSAGES/django.po
colorfield/locale/it/LC_MESSAGES/django.mo
colorfield/locale/it/LC_MESSAGES/django.po
colorfield/static/colorfield/colorfield.js
colorfield/static/colorfield/jscolor/jscolor.js
colorfield/static/colorfield/jscolor/jscolor.min.js
colorfield/templates/colorfield/color.html
django_colorfield-0.11.0.dist-info/LICENSE.txt
django_colorfield-0.11.0.dist-info/METADATA
django_colorfield-0.11.0.dist-info/WHEEL
django_colorfield-0.11.0.dist-info/top_level.txt
django_colorfield-0.11.0.dist-info/RECORD
