Metadata-Version: 2.1
Name: django-colorfield
Version: 0.11.0
Summary: color field for django models with a nice color-picker in the admin.
Author-email: Jared Forsyth <jared@jaredforsyth.com>, Fabio Caccamo <fabio.caccamo@gmail.com>
Maintainer-email: Fabio Caccamo <fabio.caccamo@gmail.com>
License: MIT License
Project-URL: Homepage, https://github.com/fabiocaccamo/django-colorfield
Project-URL: Download, https://github.com/fabiocaccamo/django-colorfield/releases
Project-URL: Documentation, https://github.com/fabiocaccamo/django-colorfield#readme
Project-URL: Issues, https://github.com/fabiocaccamo/django-colorfield/issues
Project-URL: Funding, https://github.com/sponsors/fabiocaccamo/
Project-URL: Twitter, https://twitter.com/fabiocaccamo
Keywords: django,colorfield,colorpicker,color,field,picker,chooser,admin,python
Classifier: Development Status :: 5 - Production/Stable
Classifier: Environment :: Web Environment
Classifier: Framework :: Django
Classifier: Framework :: Django :: 3.0
Classifier: Framework :: Django :: 3.1
Classifier: Framework :: Django :: 3.2
Classifier: Framework :: Django :: 4.0
Classifier: Framework :: Django :: 4.1
Classifier: Framework :: Django :: 4.2
Classifier: Framework :: Django :: 5.0
Classifier: Intended Audience :: Developers
Classifier: License :: OSI Approved :: MIT License
Classifier: Natural Language :: English
Classifier: Operating System :: OS Independent
Classifier: Programming Language :: Python :: 3
Classifier: Programming Language :: Python :: 3.8
Classifier: Programming Language :: Python :: 3.9
Classifier: Programming Language :: Python :: 3.10
Classifier: Programming Language :: Python :: 3.11
Classifier: Programming Language :: Python :: 3.12
Classifier: Topic :: Software Development :: Build Tools
License-File: LICENSE.txt
Requires-Dist: Pillow>=9.0.0
